{
  "$schema": "https://developer.microsoft.com/json-schemas/fabric/item/report/definition/visualContainer/1.0.0/schema.json",
  "name": "p5SlicerProduct",
  "position": {
    "x": 8,
    "y": 574,
    "z": 8,
    "width": 184,
    "height": 62
  },
  "visual": {
    "visualType": "slicer",
    "query": {
      "queryState": {
        "Values": {
          "projections": [
            {
              "field": {
                "Column": {
                  "Expression": {
                    "SourceRef": {
                      "Entity": "NIKON"
                    }
                  },
                  "Property": "PRODUCT"
                }
              },
              "queryRef": "NIKON.PRODUCT",
              "nativeQueryRef": "PRODUCT"
            }
          ]
        }
      }
    },
    "objects": {
      "data": [
        {
          "properties": {
            "mode": {
              "expr": {
                "Literal": {
                  "Value": "'Dropdown'"
                }
              }
            }
          }
        }
      ]
    },
    "drillFilterOtherVisuals": true
  }
}
